Uranus/AboutWindow.py
Uranus/Analyzer.py
Uranus/AstDetection.py
Uranus/Cell.py
Uranus/CodeEditor.py
Uranus/CodeHighlight.py
Uranus/DataOutputEditor.py
Uranus/DocumentEditor.py
Uranus/ImageOutput.py
Uranus/MainWindow.py
Uranus/MarkdownEditor.py
Uranus/ObjectInspectorWindow.py
Uranus/OutputEditor.py
Uranus/PyCodeEditor.py
Uranus/PythonTemplate.py
Uranus/SettingWindow.py
Uranus/WorkWindow.py
Uranus/WorkWindowPython.py
Uranus/__init__.py
Uranus/__main__.py
Uranus/core.py
Uranus/utils.py
Uranus/font/FiraCode-VariableFont_wght.ttf
Uranus/font/JetBrainsMono-Light.ttf
Uranus/font/JetBrainsMono-Medium.ttf
Uranus/font/ShareTechMono-Regular.ttf
Uranus/font/SpaceMono-Regular.ttf
Uranus/font/Technology.ttf
Uranus/font/UbuntuMono-Regular.ttf
Uranus/font/__init__.py
Uranus/image/Chart.png
Uranus/image/File_Tree.png
Uranus/image/Uranus.png
Uranus/image/a sleek futuristic2 i.png
Uranus/image/add_file.png
Uranus/image/add_folder.png
Uranus/image/add_py_file.png
Uranus/image/bold.png
Uranus/image/center.png
Uranus/image/clear.png
Uranus/image/clear_format.png
Uranus/image/code_analyzer.png
Uranus/image/color.png
Uranus/image/create_project.png
Uranus/image/csv.png
Uranus/image/db.png
Uranus/image/delete_file.png
Uranus/image/delete_folder.png
Uranus/image/delete_page.png
Uranus/image/detach.png
Uranus/image/doc_Type.png
Uranus/image/doc_delete.png
Uranus/image/down.png
Uranus/image/file_unknown.png
Uranus/image/folder.png
Uranus/image/font.png
Uranus/image/graph.png
Uranus/image/image.png
Uranus/image/insert_image.png
Uranus/image/iptopy.png
Uranus/image/ipynb_icon.png
Uranus/image/ipython_file_add.png
Uranus/image/italic.png
Uranus/image/json.png
Uranus/image/justify.png
Uranus/image/left.png
Uranus/image/load_file.png
Uranus/image/ltr.png
Uranus/image/memory.png
Uranus/image/move_down.png
Uranus/image/move_up.png
Uranus/image/print.png
Uranus/image/prj_folder.png
Uranus/image/python_icon.png
Uranus/image/resize.png
Uranus/image/right.png
Uranus/image/rtl.png
uranus_ide-3.2.1a28.dist-info/licenses/LICENSE
uranus_ide-3.2.1a28.dist-info/METADATA
uranus_ide-3.2.1a28.dist-info/WHEEL
uranus_ide-3.2.1a28.dist-info/entry_points.txt
uranus_ide-3.2.1a28.dist-info/top_level.txt
uranus_ide-3.2.1a28.dist-info/RECORD
