Metadata-Version: 2.4
Name: Uranus-IDE
Version: 3.2.1a28
Summary: A lightweight, extensible Python IDE inspired by Jupyter, built with PyQt5.
Home-page: https://github.com/atila-gh/Uranus-IDE
Author: Atila Ghashghaie
Author-email: Atila Ghashghaie <atila.gh@gmail.com>
License-Expression: LicenseRef-Atila
Project-URL: Homepage, https://github.com/atila-gh/Uranus-IDE
Project-URL: Documentation, https://github.com/atila-gh/Uranus-IDE/wiki
Project-URL: Issues, https://github.com/atila-gh/Uranus-IDE/issues
Requires-Python: >=3.8
License-File: LICENSE
Requires-Dist: PyQt5
Requires-Dist: IPython
Requires-Dist: nbformat
Requires-Dist: markdown2
Requires-Dist: html2text
Requires-Dist: Pillow
Requires-Dist: ruff
Dynamic: license-file
